README
setup.py
pybehnevis/__init__.py
pybehnevis.egg-info/PKG-INFO
pybehnevis.egg-info/SOURCES.txt
pybehnevis.egg-info/dependency_links.txt
pybehnevis.egg-info/top_level.txt