Metadata-Version: 1.1
Name: pybehnevis
Version: 0.1.1
Summary: python wrapper for Behnevis API
Home-page: https://github.com/mamins1376/PyBehnevis/
Author: Mohammad Amin Sameti
Author-email: mamins1376@gmail.com
License: GNU General Public License v3 or later
Keywords: pybehnevis api wrapper python3
Platform: UNKNOWN
Classifier: License :: OSI Approved :: GNU General Public License v3 or later (GPLv3+)
Classifier: Topic :: Software Development
Classifier: Topic :: Internet :: WWW/HTTP
Classifier: Programming Language :: Python :: 3
Classifier: Operating System :: OS Independent
Classifier: Development Status :: 4 - Beta
